main_dec/__init__.py
main_dec-0.1.1.dist-info/WHEEL
main_dec-0.1.1.dist-info/METADATA
main_dec-0.1.1.dist-info/RECORD
