Metadata-Version: 2.1
Name: main-dec
Version: 0.1.1
Summary: A tiny library for creating CLIs
Home-page: https://github.com/suned/main-dec
Author: Sune Debel
Author-email: sad@archii.ai
Requires-Python: >=3.6,<4.0
Classifier: Programming Language :: Python :: 3
Classifier: Programming Language :: Python :: 3.6
Classifier: Programming Language :: Python :: 3.7
Requires-Dist: docstring-parser (>=0.3.0,<0.4.0)
Requires-Dist: stringcase (>=1.2,<2.0)
